qlass/__init__.py
qlass/compiler/__init__.py
qlass/compiler/compiler.py
qlass/compiler/hardware_config.py
qlass/py.typed
qlass/quantum_chemistry/__init__.py
qlass/quantum_chemistry/classical_solution.py
qlass/quantum_chemistry/hamiltonians.py
qlass/utils/__init__.py
qlass/utils/utils.py
qlass/vqe/__init__.py
qlass/vqe/ansatz.py
qlass/vqe/vqe.py
qlass-0.2.1.dist-info/licenses/LICENSE
qlass-0.2.1.dist-info/WHEEL
qlass-0.2.1.dist-info/METADATA
qlass-0.2.1.dist-info/RECORD
