Metadata-Version: 2.4
Name: qlass
Version: 0.2.1
Summary: VQE on linear optical circuits
Author: Farrokh Labib
Author-email: Farrokh Labib <farrokh@unitary.foundation>
License-Expression: Apache-2.0
License-File: LICENSE
Classifier: Programming Language :: Python
Classifier: Programming Language :: Python :: 3 :: Only
Classifier: Programming Language :: Python :: 3.10
Classifier: Programming Language :: Python :: 3.11
Classifier: Programming Language :: Python :: 3.12
Classifier: Programming Language :: Python :: 3.13
Classifier: Typing :: Typed
Requires-Dist: qiskit>=2.0.0
Requires-Dist: numpy>=2.1 ; python_full_version >= '3.13'
Requires-Dist: numpy>=1.26 ; python_full_version >= '3.12'
Requires-Dist: numpy>=1.24 ; python_full_version >= '3.11'
Requires-Dist: numpy>=1.22
Requires-Dist: qiskit-aer>=0.17.0
Requires-Dist: perceval-quandela>=0.13.2,<1.0.0
Requires-Dist: piquasso>=7.1.0
Requires-Dist: openfermionpyscf>=0.5
Requires-Dist: tqdm>=4.67.1
Requires-Dist: numba>=0.59.0 ; python_full_version < '3.13'
Requires-Dist: numba>=0.61.0 ; python_full_version >= '3.13'
Requires-Python: >=3.10
Project-URL: Homepage, https://github.com/unitaryfoundation/qlass
Project-URL: Issues, https://github.com/unitaryfoundation/qlass/issues
